setup.py
bin/yelp_cli.py
yelp_api_client.egg-info/PKG-INFO
yelp_api_client.egg-info/SOURCES.txt
yelp_api_client.egg-info/dependency_links.txt
yelp_api_client.egg-info/top_level.txt
yelpclient/__init__.py
yelpclient/client.py