Metadata-Version: 1.0
Name: yelp-api-client
Version: 0.0.1
Summary: Client library for Yelp API
Home-page: https://github.com/tazzy531/YelpClient
Author: Johnie Lee
Author-email: johnie@johnia.com
License: UNKNOWN
Platform: UNKNOWN
